{
  "history": [
    {
      "id": 197,
      "station_id": 2,
      "artist": "Madonna",
      "title": "Express Yourself",
      "text": "Madonna — Express Yourself",
      "url": "https://www.shazam.com/track/223507/express-yourself",
      "shazam_key": "223507",
      "recognized_at": "2026-07-13T15:05:34Z",
      "created_at": "2026-07-13 15:05:45",
      "station_slug": "galgalatz",
      "station_name": "גלגלצ",
      "station_color": "#e36a6a"
    },
    {
      "id": 190,
      "station_id": 2,
      "artist": "Scraps Orchestra",
      "title": "Mondonuovo",
      "text": "Scraps Orchestra — Mondonuovo",
      "url": "https://www.shazam.com/track/274997326/mondonuovo",
      "shazam_key": "274997326",
      "recognized_at": "2026-07-13T15:00:27Z",
      "created_at": "2026-07-13 15:00:45",
      "station_slug": "galgalatz",
      "station_name": "גלגלצ",
      "station_color": "#e36a6a"
    },
    {
      "id": 184,
      "station_id": 2,
      "artist": "Prince",
      "title": "Nothing Compares 2 U",
      "text": "Prince — Nothing Compares 2 U",
      "url": "https://www.shazam.com/track/11176212/nothing-compares-2-u",
      "shazam_key": "11176212",
      "recognized_at": "2026-07-13T14:55:18Z",
      "created_at": "2026-07-13 14:55:19",
      "station_slug": "galgalatz",
      "station_name": "גלגלצ",
      "station_color": "#e36a6a"
    },
    {
      "id": 183,
      "station_id": 2,
      "artist": "Aretha Franklin",
      "title": "Chain of Fools",
      "text": "Aretha Franklin — Chain of Fools",
      "url": "https://www.shazam.com/track/2906435/chain-of-fools",
      "shazam_key": "2906435",
      "recognized_at": "2026-07-13T14:54:17Z",
      "created_at": "2026-07-13 14:54:19",
      "station_slug": "galgalatz",
      "station_name": "גלגלצ",
      "station_color": "#e36a6a"
    },
    {
      "id": 178,
      "station_id": 2,
      "artist": "The Cardigans",
      "title": "My Favourite Game",
      "text": "The Cardigans — My Favourite Game",
      "url": "https://www.shazam.com/track/247855/my-favourite-game",
      "shazam_key": "247855",
      "recognized_at": "2026-07-13T14:51:13Z",
      "created_at": "2026-07-13 14:51:15",
      "station_slug": "galgalatz",
      "station_name": "גלגלצ",
      "station_color": "#e36a6a"
    },
    {
      "id": 174,
      "station_id": 2,
      "artist": "Ninet Tayeb",
      "title": "בינתיים לך איתה",
      "text": "Ninet Tayeb — בינתיים לך איתה",
      "url": "https://www.shazam.com/track/878812413/%D7%91%D7%99%D7%A0%D7%AA%D7%99%D7%99%D7%9D-%D7%9C%D7%9A-%D7%90%D7%99%D7%AA%D7%94",
      "shazam_key": "878812413",
      "recognized_at": "2026-07-13T14:48:09Z",
      "created_at": "2026-07-13 14:48:15",
      "station_slug": "galgalatz",
      "station_name": "גלגלצ",
      "station_color": "#e36a6a"
    },
    {
      "id": 169,
      "station_id": 2,
      "artist": "Knesiyat Hasechel",
      "title": "ידיים למעלה",
      "text": "Knesiyat Hasechel — ידיים למעלה",
      "url": "https://www.shazam.com/track/255243667/%D7%99%D7%93%D7%99%D7%99%D7%9D-%D7%9C%D7%9E%D7%A2%D7%9C%D7%94",
      "shazam_key": "255243667",
      "recognized_at": "2026-07-13T14:43:00Z",
      "created_at": "2026-07-13 14:43:15",
      "station_slug": "galgalatz",
      "station_name": "גלגלצ",
      "station_color": "#e36a6a"
    },
    {
      "id": 165,
      "station_id": 2,
      "artist": "Jungle",
      "title": "Carry On",
      "text": "Jungle — Carry On",
      "url": "https://www.shazam.com/track/869308214/carry-on",
      "shazam_key": "869308214",
      "recognized_at": "2026-07-13T14:39:55Z",
      "created_at": "2026-07-13 14:40:15",
      "station_slug": "galgalatz",
      "station_name": "גלגלצ",
      "station_color": "#e36a6a"
    },
    {
      "id": 161,
      "station_id": 2,
      "artist": "Michael Kiwanuka",
      "title": "Black Man in a White World",
      "text": "Michael Kiwanuka — Black Man in a White World",
      "url": "https://www.shazam.com/track/309638003/black-man-in-a-white-world",
      "shazam_key": "309638003",
      "recognized_at": "2026-07-13T14:35:49Z",
      "created_at": "2026-07-13 14:36:15",
      "station_slug": "galgalatz",
      "station_name": "גלגלצ",
      "station_color": "#e36a6a"
    },
    {
      "id": 157,
      "station_id": 2,
      "artist": "Silk City",
      "title": "Only Can Get Better (Original Mix)",
      "text": "Silk City — Only Can Get Better (Original Mix)",
      "url": "https://www.shazam.com/track/423033479/only-can-get-better-original-mix",
      "shazam_key": "423033479",
      "recognized_at": "2026-07-13T14:32:45Z",
      "created_at": "2026-07-13 14:32:45",
      "station_slug": "galgalatz",
      "station_name": "גלגלצ",
      "station_color": "#e36a6a"
    },
    {
      "id": 149,
      "station_id": 2,
      "artist": "Lea Shabat",
      "title": "חתיכת שמיים",
      "text": "Lea Shabat — חתיכת שמיים",
      "url": "https://www.shazam.com/track/200696301/%D7%97%D7%AA%D7%99%D7%9B%D7%AA-%D7%A9%D7%9E%D7%99%D7%99%D7%9D",
      "shazam_key": "200696301",
      "recognized_at": "2026-07-13T14:27:37Z",
      "created_at": "2026-07-13 14:27:45",
      "station_slug": "galgalatz",
      "station_name": "גלגלצ",
      "station_color": "#e36a6a"
    },
    {
      "id": 145,
      "station_id": 2,
      "artist": "Taylor Swift",
      "title": "I Knew It, I Knew You (From \"Toy Story 5\")",
      "text": "Taylor Swift — I Knew It, I Knew You (From \"Toy Story 5\")",
      "url": "https://www.shazam.com/track/881335906/i-knew-it-i-knew-you-from-toy-story-5",
      "shazam_key": "881335906",
      "recognized_at": "2026-07-13T14:24:31Z",
      "created_at": "2026-07-13 14:24:45",
      "station_slug": "galgalatz",
      "station_name": "גלגלצ",
      "station_color": "#e36a6a"
    },
    {
      "id": 142,
      "station_id": 2,
      "artist": "Leona Lewis",
      "title": "Bleeding Love",
      "text": "Leona Lewis — Bleeding Love",
      "url": "https://www.shazam.com/track/45848405/bleeding-love",
      "shazam_key": "45848405",
      "recognized_at": "2026-07-13T14:20:25Z",
      "created_at": "2026-07-13 14:20:45",
      "station_slug": "galgalatz",
      "station_name": "גלגלצ",
      "station_color": "#e36a6a"
    },
    {
      "id": 136,
      "station_id": 2,
      "artist": "Ethnix",
      "title": "מתי לחזור",
      "text": "Ethnix — מתי לחזור",
      "url": "https://www.shazam.com/track/200451014/%D7%9E%D7%AA%D7%99-%D7%9C%D7%97%D7%96%D7%95%D7%A8",
      "shazam_key": "200451014",
      "recognized_at": "2026-07-13T14:14:16Z",
      "created_at": "2026-07-13 14:14:19",
      "station_slug": "galgalatz",
      "station_name": "גלגלצ",
      "station_color": "#e36a6a"
    },
    {
      "id": 132,
      "station_id": 2,
      "artist": "Roei Adam",
      "title": "אבי הטחול",
      "text": "Roei Adam — אבי הטחול",
      "url": "https://www.shazam.com/track/884063813/%D7%90%D7%91%D7%99-%D7%94%D7%98%D7%97%D7%95%D7%9C",
      "shazam_key": "884063813",
      "recognized_at": "2026-07-13T14:11:12Z",
      "created_at": "2026-07-13 14:11:15",
      "station_slug": "galgalatz",
      "station_name": "גלגלצ",
      "station_color": "#e36a6a"
    },
    {
      "id": 124,
      "station_id": 2,
      "artist": "Youssou N'Dour",
      "title": "7 Seconds (feat. Neneh Cherry)",
      "text": "Youssou N'Dour — 7 Seconds (feat. Neneh Cherry)",
      "url": "https://www.shazam.com/track/310953/7-seconds-feat-neneh-cherry",
      "shazam_key": "310953",
      "recognized_at": "2026-07-13T14:05:04Z",
      "created_at": "2026-07-13 14:05:15",
      "station_slug": "galgalatz",
      "station_name": "גלגלצ",
      "station_color": "#e36a6a"
    },
    {
      "id": 116,
      "station_id": 2,
      "artist": "Sheygets",
      "title": "Hamilim Hachi Yafot (המילים הכי יפות)",
      "text": "Sheygets — Hamilim Hachi Yafot (המילים הכי יפות)",
      "url": "https://www.shazam.com/track/247040602/hamilim-hachi-yafot-%D7%94%D7%9E%D7%99%D7%9C%D7%99%D7%9D-%D7%94%D7%9B%D7%99-%D7%99%D7%A4%D7%95%D7%AA",
      "shazam_key": "247040602",
      "recognized_at": "2026-07-13T13:56:51Z",
      "created_at": "2026-07-13 13:57:15",
      "station_slug": "galgalatz",
      "station_name": "גלגלצ",
      "station_color": "#e36a6a"
    },
    {
      "id": 110,
      "station_id": 2,
      "artist": "Olivia Rodrigo",
      "title": "stupid song",
      "text": "Olivia Rodrigo — stupid song",
      "url": "https://www.shazam.com/track/870957851/stupid-song",
      "shazam_key": "870957851",
      "recognized_at": "2026-07-13T13:52:45Z",
      "created_at": "2026-07-13 13:52:45",
      "station_slug": "galgalatz",
      "station_name": "גלגלצ",
      "station_color": "#e36a6a"
    },
    {
      "id": 106,
      "station_id": 2,
      "artist": "Rihanna",
      "title": "Where Have You Been",
      "text": "Rihanna — Where Have You Been",
      "url": "https://www.shazam.com/track/54051188/where-have-you-been",
      "shazam_key": "54051188",
      "recognized_at": "2026-07-13T13:48:46Z",
      "created_at": "2026-07-13 13:48:55",
      "station_slug": "galgalatz",
      "station_name": "גלגלצ",
      "station_color": "#e36a6a"
    },
    {
      "id": 105,
      "station_id": 2,
      "artist": "Jungle",
      "title": "All of the Time (DJ Streaks Remix)",
      "text": "Jungle — All of the Time (DJ Streaks Remix)",
      "url": "https://www.shazam.com/track/585052710/all-of-the-time-dj-streaks-remix",
      "shazam_key": "585052710",
      "recognized_at": "2026-07-13T13:47:44Z",
      "created_at": "2026-07-13 13:47:55",
      "station_slug": "galgalatz",
      "station_name": "גלגלצ",
      "station_color": "#e36a6a"
    },
    {
      "id": 100,
      "station_id": 2,
      "artist": "Paradisio",
      "title": "Bailando",
      "text": "Paradisio — Bailando",
      "url": "https://www.shazam.com/track/10519101/bailando",
      "shazam_key": "10519101",
      "recognized_at": "2026-07-13T13:43:39Z",
      "created_at": "2026-07-13 13:43:55",
      "station_slug": "galgalatz",
      "station_name": "גלגלצ",
      "station_color": "#e36a6a"
    },
    {
      "id": 97,
      "station_id": 2,
      "artist": "Carakukly & Liad Meir",
      "title": "פבלו אסקובר",
      "text": "Carakukly & Liad Meir — פבלו אסקובר",
      "url": "https://www.shazam.com/track/874459024/%D7%A4%D7%91%D7%9C%D7%95-%D7%90%D7%A1%D7%A7%D7%95%D7%91%D7%A8",
      "shazam_key": "874459024",
      "recognized_at": "2026-07-13T13:40:32Z",
      "created_at": "2026-07-13 13:40:35",
      "station_slug": "galgalatz",
      "station_name": "גלגלצ",
      "station_color": "#e36a6a"
    },
    {
      "id": 94,
      "station_id": 2,
      "artist": "Jasmin Moallem",
      "title": "תן לי את האששש",
      "text": "Jasmin Moallem — תן לי את האששש",
      "url": "https://www.shazam.com/track/806003760/%D7%AA%D7%9F-%D7%9C%D7%99-%D7%90%D7%AA-%D7%94%D7%90%D7%A9%D7%A9%D7%A9",
      "shazam_key": "806003760",
      "recognized_at": "2026-07-13T13:37:28Z",
      "created_at": "2026-07-13 13:37:35",
      "station_slug": "galgalatz",
      "station_name": "גלגלצ",
      "station_color": "#e36a6a"
    },
    {
      "id": 88,
      "station_id": 2,
      "artist": "The Pointer Sisters",
      "title": "I'm So Excited",
      "text": "The Pointer Sisters — I'm So Excited",
      "url": "https://www.shazam.com/track/51913201/im-so-excited",
      "shazam_key": "51913201",
      "recognized_at": "2026-07-13T13:33:44Z",
      "created_at": "2026-07-13 13:34:05",
      "station_slug": "galgalatz",
      "station_name": "גלגלצ",
      "station_color": "#e36a6a"
    },
    {
      "id": 79,
      "station_id": 2,
      "artist": "Ha'Eivrit",
      "title": "Mesibat Kita",
      "text": "Ha'Eivrit — Mesibat Kita",
      "url": "https://www.shazam.com/track/58554077/mesibat-kita",
      "shazam_key": "58554077",
      "recognized_at": "2026-07-13T13:27:35Z",
      "created_at": "2026-07-13 13:28:05",
      "station_slug": "galgalatz",
      "station_name": "גלגלצ",
      "station_color": "#e36a6a"
    }
  ],
  "total": 25,
  "updated_at": "2026-07-13T15:10:15Z"
}
