[{"id":1485,"station_id":1,"artist":"Rick Astley","title":"Never Gonna Give You Up","text":"Rick Astley — Never Gonna Give You Up","url":"https://www.shazam.com/track/357027/never-gonna-give-you-up","shazam_key":"357027","recognized_at":"2026-07-14T07:18:27Z","created_at":"2026-07-14 07:18:44","isrc":"GBARL9300135","station_slug":"kol-hashfela","station_name":"קול השפלה 103.6FM","station_color":"#6ae3c1"},{"id":1483,"station_id":2,"artist":"Monica Sex","title":"מכה אפורה","text":"Monica Sex — מכה אפורה","url":"https://www.shazam.com/track/56148359/%D7%9E%D7%9B%D7%94-%D7%90%D7%A4%D7%95%D7%A8%D7%94","shazam_key":"56148359","recognized_at":"2026-07-14T07:15:29Z","created_at":"2026-07-14 07:15:44","isrc":"IL1000000760","station_slug":"galgalatz","station_name":"גלגלצ","station_color":"#e36a6a"},{"id":1486,"station_id":3,"artist":"Desireless","title":"Voyage voyage","text":"Desireless — Voyage voyage","url":"https://www.shazam.com/track/40223639/voyage-voyage","shazam_key":"40223639","recognized_at":"2026-07-14T07:19:12Z","created_at":"2026-07-14 07:19:24","isrc":"DEQ858600201","station_slug":"99fm","station_name":"99FM","station_color":"#6ab8e3"},{"id":1484,"station_id":4,"artist":"Beyoncé","title":"Xo","text":"Beyoncé — Xo","url":"https://www.shazam.com/track/103651895/xo","shazam_key":"103651895","recognized_at":"2026-07-14T07:16:12Z","created_at":"2026-07-14 07:16:24","isrc":"USSM11307807","station_slug":"radio-tlv","station_name":"רדיו תל אביב 102FM","station_color":"#e3c86a"},{"id":1482,"station_id":5,"artist":"Desireless","title":"Voyage voyage (Maxi)","text":"Desireless — Voyage voyage (Maxi)","url":"https://www.shazam.com/track/50603262/voyage-voyage-maxi","shazam_key":"50603262","recognized_at":"2026-07-14T07:14:34Z","created_at":"2026-07-14 07:14:44","isrc":"DEQ858600202","station_slug":"kan-88","station_name":"כאן 88","station_color":"#c86ae3"},{"id":1460,"station_id":6,"artist":"Roie Shpigler & Ziv Moran","title":"Northland","text":"Roie Shpigler & Ziv Moran — Northland","url":"https://www.shazam.com/track/876599256/northland","shazam_key":"876599256","recognized_at":"2026-07-14T06:53:22Z","created_at":"2026-07-14 06:53:24","isrc":"IL6652605323","station_slug":"kan-bet","station_name":"כאן ב","station_color":"#e38a6a"},{"id":1479,"station_id":7,"artist":"Ronan Keating & Robbie Williams","title":"The Big Goodbye","text":"Ronan Keating & Robbie Williams — The Big Goodbye","url":"https://www.shazam.com/track/511925995/the-big-goodbye","shazam_key":"511925995","recognized_at":"2026-07-14T07:12:33Z","created_at":"2026-07-14 07:12:44","isrc":"GBUM72000339","station_slug":"galil","station_name":"קול הגליל העליון","station_color":"#a06ae3"},{"id":1443,"station_id":8,"artist":"Sherri","title":"דם חם","text":"Sherri — דם חם","url":"https://www.shazam.com/track/201504219/%D7%93%D7%9D-%D7%97%D7%9D","shazam_key":"201504219","recognized_at":"2026-07-14T06:39:45Z","created_at":"2026-07-14 06:40:04","isrc":"IL4641900244","station_slug":"radio-darom","station_name":"רדיו דרום 97FM","station_color":"#e36ac8"}]
