{"windows":{"1h":{"artists":[{"artist":"Sting","count":4,"stations":{"galil":2,"kol-hashfela":1,"radio-darom":1},"prev":1},{"artist":"Beyoncé","count":2,"stations":{"galil":2},"prev":1},{"artist":"Faith No More","count":2,"stations":{"galgalatz":1,"99fm":1},"prev":0},{"artist":"Nathan Goshen","count":2,"stations":{"kol-hashfela":1,"99fm":1},"prev":0},{"artist":"Eyal Golan","count":2,"stations":{"radio-darom":2},"prev":1},{"artist":"Sting & Kurt","count":1,"stations":{"galil":1},"prev":0},{"artist":"The Beatles","count":1,"stations":{"radio-tlv":1},"prev":0},{"artist":"Hanan Ben Ari","count":1,"stations":{"galgalatz":1},"prev":0},{"artist":"Aves & Vincent Parker","count":1,"stations":{"radio-tlv":1},"prev":0},{"artist":"Corinne Allal","count":1,"stations":{"kol-hashfela":1},"prev":0},{"artist":"Mike Oldfield","count":1,"stations":{"99fm":1},"prev":0},{"artist":"Frank Ocean","count":1,"stations":{"galgalatz":1},"prev":0},{"artist":"James Arthur","count":1,"stations":{"kol-hashfela":1},"prev":0},{"artist":"Akiva","count":1,"stations":{"radio-darom":1},"prev":0},{"artist":"JAŸ-Z","count":1,"stations":{"galil":1},"prev":0},{"artist":"The Lumineers","count":1,"stations":{"99fm":1},"prev":0},{"artist":"Plain White T's","count":1,"stations":{"radio-tlv":1},"prev":0},{"artist":"Paul Young","count":1,"stations":{"kol-hashfela":1},"prev":0},{"artist":"Arik Einstein","count":1,"stations":{"radio-darom":1},"prev":0},{"artist":"Anni B Sweet","count":1,"stations":{"galil":1},"prev":0},{"artist":"Amy Winehouse","count":1,"stations":{"galgalatz":1},"prev":0},{"artist":"Rita & Meshi Kleinstein","count":1,"stations":{"radio-tlv":1},"prev":0},{"artist":"R.E.M.","count":1,"stations":{"99fm":1},"prev":0},{"artist":"Semisonic","count":1,"stations":{"radio-darom":1},"prev":0},{"artist":"Haim Moshe","count":1,"stations":{"galgalatz":1},"prev":0},{"artist":"Gil Vain & נופיה","count":1,"stations":{"kan-bet":1},"prev":0},{"artist":"Alanis Morissette","count":1,"stations":{"99fm":1},"prev":0},{"artist":"Gnarls Barkley","count":1,"stations":{"radio-tlv":1},"prev":0},{"artist":"Guns N' Roses","count":1,"stations":{"kol-hashfela":1},"prev":0},{"artist":"Omer Adam","count":1,"stations":{"radio-darom":1},"prev":1},{"artist":"Bar Tzabari","count":1,"stations":{"galgalatz":1},"prev":0},{"artist":"Iggy Waxman","count":1,"stations":{"kan-bet":1},"prev":0},{"artist":"Eviatar Banai","count":1,"stations":{"kol-hashfela":1},"prev":1},{"artist":"Ran Danker","count":1,"stations":{"radio-tlv":1},"prev":0},{"artist":"Yehudit Ravitz","count":1,"stations":{"99fm":1},"prev":0},{"artist":"Shlomo Artzi","count":1,"stations":{"kan-88":1},"prev":0},{"artist":"Beit Habubot & אמיר אטיאס","count":1,"stations":{"kan-bet":1},"prev":0},{"artist":"Hatikva 6","count":1,"stations":{"radio-darom":1},"prev":0},{"artist":"Lauryn Hill","count":1,"stations":{"galil":1},"prev":0},{"artist":"Alice Merton","count":1,"stations":{"galgalatz":1},"prev":0},{"artist":"Roie Shpigler & Ziv Moran","count":1,"stations":{"kan-bet":1},"prev":1},{"artist":"Sufjan Stevens","count":1,"stations":{"99fm":1},"prev":0},{"artist":"ABBA","count":1,"stations":{"radio-tlv":1},"prev":0},{"artist":"Modjo","count":1,"stations":{"radio-darom":1},"prev":0},{"artist":"Depeche Mode","count":1,"stations":{"galil":1},"prev":0},{"artist":"Cat Stevens","count":1,"stations":{"99fm":1},"prev":0},{"artist":"Imagine Dragons","count":1,"stations":{"radio-tlv":1},"prev":0},{"artist":"Guy & Yahel","count":1,"stations":{"galgalatz":1},"prev":0},{"artist":"Ravid Plotnik","count":1,"stations":{"kol-hashfela":1},"prev":0},{"artist":"Tomer Yosef","count":1,"stations":{"radio-darom":1},"prev":0}],"songs":[{"artist":"Sting","count":1,"stations":{"galil":1},"title":"For Her Love","prev":0},{"artist":"Sting & Kurt","count":1,"stations":{"galil":1},"title":"Por Su Amor","prev":0},{"artist":"The Beatles","count":1,"stations":{"radio-tlv":1},"title":"Michelle","prev":0},{"artist":"Sting","count":1,"stations":{"galil":1},"title":"Por Su Amor","prev":0},{"artist":"Hanan Ben Ari","count":1,"stations":{"galgalatz":1},"title":"ויקיפדיה","prev":0},{"artist":"Aves & Vincent Parker","count":1,"stations":{"radio-tlv":1},"title":"Testify","prev":0},{"artist":"Corinne Allal","count":1,"stations":{"kol-hashfela":1},"title":"שיר לשירה","prev":0},{"artist":"Mike Oldfield","count":1,"stations":{"99fm":1},"title":"To France","prev":0},{"artist":"Frank Ocean","count":1,"stations":{"galgalatz":1},"title":"Thinkin Bout You","prev":0},{"artist":"James Arthur","count":1,"stations":{"kol-hashfela":1},"title":"Say You Won't Let Go","prev":0},{"artist":"Akiva","count":1,"stations":{"radio-darom":1},"title":"צעדים","prev":0},{"artist":"JAŸ-Z","count":1,"stations":{"galil":1},"title":"Hard Knock Life (Ghetto Anthem)","prev":0},{"artist":"The Lumineers","count":1,"stations":{"99fm":1},"title":"Ho Hey","prev":0},{"artist":"Plain White T's","count":1,"stations":{"radio-tlv":1},"title":"Hey There Delilah","prev":0},{"artist":"Paul Young","count":1,"stations":{"kol-hashfela":1},"title":"Wherever I Lay My Hat (That's My Home)","prev":0},{"artist":"Arik Einstein","count":1,"stations":{"radio-darom":1},"title":"צליל מכוון","prev":0},{"artist":"Anni B Sweet","count":1,"stations":{"galil":1},"title":"Take On Me","prev":0},{"artist":"Amy Winehouse","count":1,"stations":{"galgalatz":1},"title":"You Know I'm No Good","prev":0},{"artist":"Rita & Meshi Kleinstein","count":1,"stations":{"radio-tlv":1},"title":"קחי לך","prev":0},{"artist":"R.E.M.","count":1,"stations":{"99fm":1},"title":"Nightswimming","prev":0},{"artist":"Beyoncé","count":1,"stations":{"galil":1},"title":"Single Ladies (Put a Ring on It)","prev":0},{"artist":"Semisonic","count":1,"stations":{"radio-darom":1},"title":"Secret Smile","prev":0},{"artist":"Haim Moshe","count":1,"stations":{"galgalatz":1},"title":"תן לזמן ללכת","prev":0},{"artist":"Gil Vain & נופיה","count":1,"stations":{"kan-bet":1},"title":"להרגיש אישה","prev":0},{"artist":"Alanis Morissette","count":1,"stations":{"99fm":1},"title":"Thank U","prev":0},{"artist":"Gnarls Barkley","count":1,"stations":{"radio-tlv":1},"title":"Crazy","prev":0},{"artist":"Guns N' Roses","count":1,"stations":{"kol-hashfela":1},"title":"Patience","prev":0},{"artist":"Beyoncé","count":1,"stations":{"galil":1},"title":"Sweet Dreams","prev":0},{"artist":"Omer Adam","count":1,"stations":{"radio-darom":1},"title":"וואי","prev":0},{"artist":"Bar Tzabari","count":1,"stations":{"galgalatz":1},"title":"ג'וני","prev":0},{"artist":"Iggy Waxman","count":1,"stations":{"kan-bet":1},"title":"Ein Li Ma Lomr Lecha","prev":0},{"artist":"Eviatar Banai","count":1,"stations":{"kol-hashfela":1},"title":"יפה כלבנה","prev":1},{"artist":"Ran Danker","count":1,"stations":{"radio-tlv":1},"title":"בית משוגעים","prev":0},{"artist":"Yehudit Ravitz","count":1,"stations":{"99fm":1},"title":"לילה","prev":0},{"artist":"Shlomo Artzi","count":1,"stations":{"kan-88":1},"title":"תגידי","prev":0},{"artist":"Beit Habubot & אמיר אטיאס","count":1,"stations":{"kan-bet":1},"title":"למעני","prev":0},{"artist":"Hatikva 6","count":1,"stations":{"radio-darom":1},"title":"לחזור הביתה","prev":0},{"artist":"Lauryn Hill","count":1,"stations":{"galil":1},"title":"Doo Wop (That Thing)","prev":0},{"artist":"Alice Merton","count":1,"stations":{"galgalatz":1},"title":"No Roots","prev":0},{"artist":"Sting","count":1,"stations":{"kol-hashfela":1},"title":"Fragile","prev":0},{"artist":"Roie Shpigler & Ziv Moran","count":1,"stations":{"kan-bet":1},"title":"Northland","prev":1},{"artist":"Sufjan Stevens","count":1,"stations":{"99fm":1},"title":"Death with Dignity","prev":0},{"artist":"ABBA","count":1,"stations":{"radio-tlv":1},"title":"Dancing Queen","prev":0},{"artist":"Modjo","count":1,"stations":{"radio-darom":1},"title":"Lady (Acoustic Version)","prev":0},{"artist":"Faith No More","count":1,"stations":{"galgalatz":1},"title":"I Started a Joke","prev":0},{"artist":"Nathan Goshen","count":1,"stations":{"kol-hashfela":1},"title":"ניצחונות קטנים","prev":0},{"artist":"Depeche Mode","count":1,"stations":{"galil":1},"title":"Personal Jesus","prev":0},{"artist":"Cat Stevens","count":1,"stations":{"99fm":1},"title":"Father and Son","prev":0},{"artist":"Imagine Dragons","count":1,"stations":{"radio-tlv":1},"title":"Demons","prev":0},{"artist":"Eyal Golan","count":1,"stations":{"radio-darom":1},"title":"מדמיין אותך","prev":0}],"total_plays":101},"24h":{"artists":[{"artist":"Faith No More","count":15,"stations":{"galgalatz":1,"99fm":1,"kan-88":13},"prev":0},{"artist":"Eyal Golan","count":10,"stations":{"radio-darom":10},"prev":0},{"artist":"Sting","count":8,"stations":{"galil":3,"kol-hashfela":3,"radio-darom":1,"99fm":1},"prev":0},{"artist":"Mark Lanegan","count":8,"stations":{"kan-88":8},"prev":0},{"artist":"Omer Adam","count":7,"stations":{"radio-darom":4,"galgalatz":1,"kan-bet":1,"radio-tlv":1},"prev":0},{"artist":"Teapacks","count":7,"stations":{"radio-tlv":1,"radio-darom":1,"kol-hashfela":3,"99fm":1,"galgalatz":1},"prev":0},{"artist":"David Bowie","count":7,"stations":{"radio-tlv":2,"99fm":2,"kol-hashfela":2,"kan-88":1},"prev":0},{"artist":"Dudu Tassa","count":6,"stations":{"99fm":1,"radio-tlv":3,"radio-darom":1,"galil":1},"prev":0},{"artist":"Madonna","count":6,"stations":{"kol-hashfela":3,"radio-tlv":1,"galgalatz":2},"prev":0},{"artist":"Tame Impala","count":6,"stations":{"radio-tlv":3,"galgalatz":1,"radio-darom":1,"kol-hashfela":1},"prev":0},{"artist":"Stevie Wonder","count":6,"stations":{"galil":1,"radio-tlv":1,"galgalatz":1,"kol-hashfela":2,"99fm":1},"prev":0},{"artist":"Peer Tasi","count":6,"stations":{"radio-darom":4,"kan-bet":1,"radio-tlv":1},"prev":0},{"artist":"Ehud Banai","count":6,"stations":{"kol-hashfela":1,"radio-darom":1,"99fm":2,"kan-88":1,"galil":1},"prev":0},{"artist":"Arik Einstein","count":5,"stations":{"radio-darom":1,"kan-88":4},"prev":0},{"artist":"Beyoncé","count":5,"stations":{"galil":2,"radio-darom":1,"galgalatz":1,"radio-tlv":1},"prev":0},{"artist":"Shlomo Artzi","count":5,"stations":{"kan-88":1,"galgalatz":1,"radio-darom":2,"kol-hashfela":1},"prev":0},{"artist":"ABBA","count":5,"stations":{"radio-tlv":3,"99fm":1,"kol-hashfela":1},"prev":0},{"artist":"Tuna","count":5,"stations":{"99fm":2,"kan-bet":1,"galgalatz":1,"radio-darom":1},"prev":0},{"artist":"Michael Jackson","count":5,"stations":{"radio-darom":1,"kol-hashfela":3,"radio-tlv":1},"prev":0},{"artist":"Renaissance","count":5,"stations":{"kan-88":5},"prev":0},{"artist":"Eden Ben Zaken","count":5,"stations":{"radio-tlv":2,"galgalatz":2,"radio-darom":1},"prev":0},{"artist":"Robert Wyatt","count":5,"stations":{"kan-88":5},"prev":0},{"artist":"Jasmin Moallem","count":5,"stations":{"kan-bet":1,"radio-tlv":1,"galil":1,"99fm":1,"galgalatz":1},"prev":0},{"artist":"The Beatles","count":4,"stations":{"radio-tlv":1,"99fm":2,"kan-bet":1},"prev":0},{"artist":"Corinne Allal","count":4,"stations":{"kol-hashfela":1,"radio-darom":1,"99fm":2},"prev":0},{"artist":"Eviatar Banai","count":4,"stations":{"kol-hashfela":2,"99fm":1,"radio-tlv":1},"prev":0},{"artist":"Nathan Goshen","count":4,"stations":{"kol-hashfela":2,"99fm":2},"prev":0},{"artist":"Pretenders","count":4,"stations":{"99fm":1,"kol-hashfela":1,"galil":2},"prev":0},{"artist":"Shuli Rand","count":4,"stations":{"radio-tlv":3,"kan-bet":1},"prev":0},{"artist":"Coldplay","count":4,"stations":{"kol-hashfela":1,"radio-darom":1,"radio-tlv":1,"99fm":1},"prev":0},{"artist":"Phil Collins","count":4,"stations":{"kol-hashfela":1,"radio-tlv":1,"99fm":1,"galil":1},"prev":0},{"artist":"Tears for Fears","count":4,"stations":{"galgalatz":1,"99fm":2,"galil":1},"prev":0},{"artist":"The Weeknd","count":4,"stations":{"99fm":1,"galgalatz":1,"radio-tlv":2},"prev":0},{"artist":"The Rolling Stones","count":4,"stations":{"galgalatz":1,"kan-88":1,"radio-tlv":1,"99fm":1},"prev":0},{"artist":"Loose Joints","count":4,"stations":{"kan-88":4},"prev":0},{"artist":"Ethnix","count":4,"stations":{"99fm":1,"kol-hashfela":2,"galgalatz":1},"prev":0},{"artist":"Yehudit Ravitz","count":3,"stations":{"99fm":3},"prev":0},{"artist":"Scorpions","count":3,"stations":{"kol-hashfela":1,"99fm":1,"radio-tlv":1},"prev":0},{"artist":"יובל מזרחי","count":3,"stations":{"radio-darom":3},"prev":0},{"artist":"Idan Raichel","count":3,"stations":{"radio-darom":2,"kol-hashfela":1},"prev":0},{"artist":"Bon Iver","count":3,"stations":{"99fm":2,"galil":1},"prev":0},{"artist":"Backstreet Boys","count":3,"stations":{"kol-hashfela":2,"radio-tlv":1},"prev":0},{"artist":"Izhar Ashdot","count":3,"stations":{"kol-hashfela":1,"galgalatz":1,"radio-tlv":1},"prev":0},{"artist":"Labrinth","count":3,"stations":{"galgalatz":3},"prev":0},{"artist":"Amir Dadon","count":3,"stations":{"radio-tlv":2,"99fm":1},"prev":0},{"artist":"Kings of Leon","count":3,"stations":{"radio-tlv":1,"99fm":1,"galil":1},"prev":0},{"artist":"Bee Gees","count":3,"stations":{"99fm":2,"radio-tlv":1},"prev":0},{"artist":"Lana Del Rey","count":3,"stations":{"radio-tlv":1,"galgalatz":1,"99fm":1},"prev":0},{"artist":"Radiohead","count":3,"stations":{"radio-tlv":1,"99fm":2},"prev":0},{"artist":"Odeya","count":3,"stations":{"radio-darom":3},"prev":0}],"songs":[{"artist":"Eyal Golan","count":7,"stations":{"radio-darom":7},"title":"מדע בדיוני","prev":0},{"artist":"Tame Impala","count":5,"stations":{"radio-tlv":3,"radio-darom":1,"kol-hashfela":1},"title":"Dracula","prev":0},{"artist":"Shuli Rand","count":4,"stations":{"radio-tlv":3,"kan-bet":1},"title":"לב לבן","prev":0},{"artist":"יובל מזרחי","count":3,"stations":{"radio-darom":3},"title":"דואט","prev":0},{"artist":"Labrinth","count":3,"stations":{"galgalatz":3},"title":"THE LIVING","prev":0},{"artist":"Dudu Tassa","count":3,"stations":{"radio-tlv":3},"title":"בית ביפו","prev":0},{"artist":"Mooki","count":3,"stations":{"radio-darom":1,"kan-88":1,"kol-hashfela":1},"title":"ילדה סוכר","prev":0},{"artist":"Jasmin Moallem","count":3,"stations":{"kan-bet":1,"radio-tlv":1,"galil":1},"title":"יהיה טוב","prev":0},{"artist":"Brill & Alona Haber","count":3,"stations":{"galgalatz":3},"title":"פרפר לבן","prev":0},{"artist":"The Doors","count":3,"stations":{"kan-88":3},"title":"Riders On The Storm","prev":0},{"artist":"Up, Bustle & Out","count":3,"stations":{"galil":3},"title":"Emerald Alley (Indian Morning Theme)","prev":0},{"artist":"Amy Winehouse","count":2,"stations":{"galgalatz":1,"99fm":1},"title":"You Know I'm No Good","prev":0},{"artist":"Eviatar Banai","count":2,"stations":{"kol-hashfela":2},"title":"יפה כלבנה","prev":0},{"artist":"Ran Danker","count":2,"stations":{"radio-tlv":1,"kol-hashfela":1},"title":"בית משוגעים","prev":0},{"artist":"Shlomo Artzi","count":2,"stations":{"kan-88":1,"radio-darom":1},"title":"תגידי","prev":0},{"artist":"Roie Shpigler & Ziv Moran","count":2,"stations":{"kan-bet":2},"title":"Northland","prev":0},{"artist":"ABBA","count":2,"stations":{"radio-tlv":2},"title":"Dancing Queen","prev":0},{"artist":"Ravid Plotnik","count":2,"stations":{"kol-hashfela":1,"99fm":1},"title":"‏שלווה בארמונותייך","prev":0},{"artist":"Scorpions","count":2,"stations":{"kol-hashfela":1,"radio-tlv":1},"title":"Still Loving You (Live)","prev":0},{"artist":"Prince","count":2,"stations":{"kol-hashfela":1,"galgalatz":1},"title":"Nothing Compares 2 U","prev":0},{"artist":"Idan Raichel","count":2,"stations":{"radio-darom":1,"kol-hashfela":1},"title":"Ahava Ka'zo (A Love Like This) [feat. זהבה בן]","prev":0},{"artist":"Backstreet Boys","count":2,"stations":{"kol-hashfela":2},"title":"Show Me the Meaning of Being Lonely","prev":0},{"artist":"Teapacks","count":2,"stations":{"radio-tlv":1,"kol-hashfela":1},"title":"התחנה הישנה","prev":0},{"artist":"Sting","count":2,"stations":{"radio-darom":1,"kol-hashfela":1},"title":"Shape Of My Heart","prev":0},{"artist":"Djo","count":2,"stations":{"radio-tlv":2},"title":"End of Beginning","prev":0},{"artist":"alt-J","count":2,"stations":{"galil":1,"radio-tlv":1},"title":"Breezeblocks","prev":0},{"artist":"Hapil Shebaheder","count":2,"stations":{"galgalatz":2},"title":"גשם אחרון","prev":0},{"artist":"Michael Jackson","count":2,"stations":{"radio-darom":1,"kol-hashfela":1},"title":"Don't Stop 'Til You Get Enough","prev":0},{"artist":"Omer Adam","count":2,"stations":{"radio-darom":2},"title":"חי (שיר הנושא מתוך לשחרר את שולי סאן)","prev":0},{"artist":"Lana Del Rey","count":2,"stations":{"radio-tlv":1,"galgalatz":1},"title":"Summertime Sadness","prev":0},{"artist":"Noam Bettan & כאן - תאגיד השידור הישראלי","count":2,"stations":{"radio-tlv":2},"title":"Michelle","prev":0},{"artist":"George Michael","count":2,"stations":{"kol-hashfela":2},"title":"Father Figure","prev":0},{"artist":"Odeya","count":2,"stations":{"radio-darom":2},"title":"עשר רמות מעליו","prev":0},{"artist":"Stamatis Spanoudakis","count":2,"stations":{"kan-bet":2},"title":"Zi Ke Vasilevi","prev":0},{"artist":"Dire Straits","count":2,"stations":{"radio-tlv":1,"99fm":1},"title":"Sultans Of Swing","prev":0},{"artist":"Bonnie Tyler","count":2,"stations":{"kol-hashfela":2},"title":"Total Eclipse of the Heart","prev":0},{"artist":"INXS","count":2,"stations":{"kol-hashfela":1,"99fm":1},"title":"Never Tear Us Apart","prev":0},{"artist":"Tohar Kadosh","count":2,"stations":{"galgalatz":2},"title":"שמש","prev":0},{"artist":"Yehudit Ravitz & Ahuva Ozeri","count":2,"stations":{"radio-darom":2},"title":"האיש ההוא","prev":0},{"artist":"Tears for Fears","count":2,"stations":{"galgalatz":1,"galil":1},"title":"Sowing The Seeds Of Love","prev":0},{"artist":"Elai Botner and Yaldei Hachutz","count":2,"stations":{"radio-tlv":1,"galgalatz":1},"title":"תתן לי יד","prev":0},{"artist":"The Weeknd","count":2,"stations":{"galgalatz":1,"radio-tlv":1},"title":"Blinding Lights","prev":0},{"artist":"TLC","count":2,"stations":{"radio-tlv":1,"kol-hashfela":1},"title":"No Scrubs","prev":0},{"artist":"Eden Hason, Ofek Adanek & Agam Buhbut","count":2,"stations":{"radio-darom":1,"galgalatz":1},"title":"איך שהיא רוקדת","prev":0},{"artist":"Balkan Beat Box","count":2,"stations":{"galil":2},"title":"Habibi Min Zaman","prev":0},{"artist":"Hadag Nahash","count":2,"stations":{"radio-darom":1,"radio-tlv":1},"title":"לזוז (feat. MC שירי)","prev":0},{"artist":"Ishay Levi","count":2,"stations":{"radio-darom":1,"radio-tlv":1},"title":"Isha Neemana","prev":0},{"artist":"Reamonn","count":2,"stations":{"radio-tlv":1,"kol-hashfela":1},"title":"Supergirl","prev":0},{"artist":"Temper City","count":2,"stations":{"radio-tlv":2},"title":"Self Aware","prev":0},{"artist":"ABBA","count":2,"stations":{"radio-tlv":1,"kol-hashfela":1},"title":"Gimme! Gimme! Gimme! (A Man After Midnight)","prev":0}],"total_plays":1045},"7d":{"artists":[{"artist":"Faith No More","count":15,"stations":{"galgalatz":1,"99fm":1,"kan-88":13},"prev":0},{"artist":"Eyal Golan","count":10,"stations":{"radio-darom":10},"prev":0},{"artist":"Sting","count":8,"stations":{"galil":3,"kol-hashfela":3,"radio-darom":1,"99fm":1},"prev":0},{"artist":"Mark Lanegan","count":8,"stations":{"kan-88":8},"prev":0},{"artist":"Omer Adam","count":7,"stations":{"radio-darom":4,"galgalatz":1,"kan-bet":1,"radio-tlv":1},"prev":0},{"artist":"Teapacks","count":7,"stations":{"radio-tlv":1,"radio-darom":1,"kol-hashfela":3,"99fm":1,"galgalatz":1},"prev":0},{"artist":"David Bowie","count":7,"stations":{"radio-tlv":2,"99fm":2,"kol-hashfela":2,"kan-88":1},"prev":0},{"artist":"Dudu Tassa","count":6,"stations":{"99fm":1,"radio-tlv":3,"radio-darom":1,"galil":1},"prev":0},{"artist":"Madonna","count":6,"stations":{"kol-hashfela":3,"radio-tlv":1,"galgalatz":2},"prev":0},{"artist":"Tame Impala","count":6,"stations":{"radio-tlv":3,"galgalatz":1,"radio-darom":1,"kol-hashfela":1},"prev":0},{"artist":"Stevie Wonder","count":6,"stations":{"galil":1,"radio-tlv":1,"galgalatz":1,"kol-hashfela":2,"99fm":1},"prev":0},{"artist":"Peer Tasi","count":6,"stations":{"radio-darom":4,"kan-bet":1,"radio-tlv":1},"prev":0},{"artist":"Ehud Banai","count":6,"stations":{"kol-hashfela":1,"radio-darom":1,"99fm":2,"kan-88":1,"galil":1},"prev":0},{"artist":"Arik Einstein","count":5,"stations":{"radio-darom":1,"kan-88":4},"prev":0},{"artist":"Beyoncé","count":5,"stations":{"galil":2,"radio-darom":1,"galgalatz":1,"radio-tlv":1},"prev":0},{"artist":"Shlomo Artzi","count":5,"stations":{"kan-88":1,"galgalatz":1,"radio-darom":2,"kol-hashfela":1},"prev":0},{"artist":"ABBA","count":5,"stations":{"radio-tlv":3,"99fm":1,"kol-hashfela":1},"prev":0},{"artist":"Tuna","count":5,"stations":{"99fm":2,"kan-bet":1,"galgalatz":1,"radio-darom":1},"prev":0},{"artist":"Michael Jackson","count":5,"stations":{"radio-darom":1,"kol-hashfela":3,"radio-tlv":1},"prev":0},{"artist":"Renaissance","count":5,"stations":{"kan-88":5},"prev":0},{"artist":"Eden Ben Zaken","count":5,"stations":{"radio-tlv":2,"galgalatz":2,"radio-darom":1},"prev":0},{"artist":"Robert Wyatt","count":5,"stations":{"kan-88":5},"prev":0},{"artist":"Jasmin Moallem","count":5,"stations":{"kan-bet":1,"radio-tlv":1,"galil":1,"99fm":1,"galgalatz":1},"prev":0},{"artist":"The Beatles","count":4,"stations":{"radio-tlv":1,"99fm":2,"kan-bet":1},"prev":0},{"artist":"Corinne Allal","count":4,"stations":{"kol-hashfela":1,"radio-darom":1,"99fm":2},"prev":0},{"artist":"Eviatar Banai","count":4,"stations":{"kol-hashfela":2,"99fm":1,"radio-tlv":1},"prev":0},{"artist":"Nathan Goshen","count":4,"stations":{"kol-hashfela":2,"99fm":2},"prev":0},{"artist":"Pretenders","count":4,"stations":{"99fm":1,"kol-hashfela":1,"galil":2},"prev":0},{"artist":"Shuli Rand","count":4,"stations":{"radio-tlv":3,"kan-bet":1},"prev":0},{"artist":"Coldplay","count":4,"stations":{"kol-hashfela":1,"radio-darom":1,"radio-tlv":1,"99fm":1},"prev":0},{"artist":"Phil Collins","count":4,"stations":{"kol-hashfela":1,"radio-tlv":1,"99fm":1,"galil":1},"prev":0},{"artist":"Tears for Fears","count":4,"stations":{"galgalatz":1,"99fm":2,"galil":1},"prev":0},{"artist":"The Weeknd","count":4,"stations":{"99fm":1,"galgalatz":1,"radio-tlv":2},"prev":0},{"artist":"The Rolling Stones","count":4,"stations":{"galgalatz":1,"kan-88":1,"radio-tlv":1,"99fm":1},"prev":0},{"artist":"Loose Joints","count":4,"stations":{"kan-88":4},"prev":0},{"artist":"Ethnix","count":4,"stations":{"99fm":1,"kol-hashfela":2,"galgalatz":1},"prev":0},{"artist":"Yehudit Ravitz","count":3,"stations":{"99fm":3},"prev":0},{"artist":"Scorpions","count":3,"stations":{"kol-hashfela":1,"99fm":1,"radio-tlv":1},"prev":0},{"artist":"יובל מזרחי","count":3,"stations":{"radio-darom":3},"prev":0},{"artist":"Idan Raichel","count":3,"stations":{"radio-darom":2,"kol-hashfela":1},"prev":0},{"artist":"Bon Iver","count":3,"stations":{"99fm":2,"galil":1},"prev":0},{"artist":"Backstreet Boys","count":3,"stations":{"kol-hashfela":2,"radio-tlv":1},"prev":0},{"artist":"Izhar Ashdot","count":3,"stations":{"kol-hashfela":1,"galgalatz":1,"radio-tlv":1},"prev":0},{"artist":"Labrinth","count":3,"stations":{"galgalatz":3},"prev":0},{"artist":"Amir Dadon","count":3,"stations":{"radio-tlv":2,"99fm":1},"prev":0},{"artist":"Kings of Leon","count":3,"stations":{"radio-tlv":1,"99fm":1,"galil":1},"prev":0},{"artist":"Bee Gees","count":3,"stations":{"99fm":2,"radio-tlv":1},"prev":0},{"artist":"Lana Del Rey","count":3,"stations":{"radio-tlv":1,"galgalatz":1,"99fm":1},"prev":0},{"artist":"Radiohead","count":3,"stations":{"radio-tlv":1,"99fm":2},"prev":0},{"artist":"Odeya","count":3,"stations":{"radio-darom":3},"prev":0}],"songs":[{"artist":"Eyal Golan","count":7,"stations":{"radio-darom":7},"title":"מדע בדיוני","prev":0},{"artist":"Tame Impala","count":5,"stations":{"radio-tlv":3,"radio-darom":1,"kol-hashfela":1},"title":"Dracula","prev":0},{"artist":"Shuli Rand","count":4,"stations":{"radio-tlv":3,"kan-bet":1},"title":"לב לבן","prev":0},{"artist":"יובל מזרחי","count":3,"stations":{"radio-darom":3},"title":"דואט","prev":0},{"artist":"Labrinth","count":3,"stations":{"galgalatz":3},"title":"THE LIVING","prev":0},{"artist":"Dudu Tassa","count":3,"stations":{"radio-tlv":3},"title":"בית ביפו","prev":0},{"artist":"Mooki","count":3,"stations":{"radio-darom":1,"kan-88":1,"kol-hashfela":1},"title":"ילדה סוכר","prev":0},{"artist":"Jasmin Moallem","count":3,"stations":{"kan-bet":1,"radio-tlv":1,"galil":1},"title":"יהיה טוב","prev":0},{"artist":"Brill & Alona Haber","count":3,"stations":{"galgalatz":3},"title":"פרפר לבן","prev":0},{"artist":"The Doors","count":3,"stations":{"kan-88":3},"title":"Riders On The Storm","prev":0},{"artist":"Up, Bustle & Out","count":3,"stations":{"galil":3},"title":"Emerald Alley (Indian Morning Theme)","prev":0},{"artist":"Amy Winehouse","count":2,"stations":{"galgalatz":1,"99fm":1},"title":"You Know I'm No Good","prev":0},{"artist":"Eviatar Banai","count":2,"stations":{"kol-hashfela":2},"title":"יפה כלבנה","prev":0},{"artist":"Ran Danker","count":2,"stations":{"radio-tlv":1,"kol-hashfela":1},"title":"בית משוגעים","prev":0},{"artist":"Shlomo Artzi","count":2,"stations":{"kan-88":1,"radio-darom":1},"title":"תגידי","prev":0},{"artist":"Roie Shpigler & Ziv Moran","count":2,"stations":{"kan-bet":2},"title":"Northland","prev":0},{"artist":"ABBA","count":2,"stations":{"radio-tlv":2},"title":"Dancing Queen","prev":0},{"artist":"Ravid Plotnik","count":2,"stations":{"kol-hashfela":1,"99fm":1},"title":"‏שלווה בארמונותייך","prev":0},{"artist":"Scorpions","count":2,"stations":{"kol-hashfela":1,"radio-tlv":1},"title":"Still Loving You (Live)","prev":0},{"artist":"Prince","count":2,"stations":{"kol-hashfela":1,"galgalatz":1},"title":"Nothing Compares 2 U","prev":0},{"artist":"Idan Raichel","count":2,"stations":{"radio-darom":1,"kol-hashfela":1},"title":"Ahava Ka'zo (A Love Like This) [feat. זהבה בן]","prev":0},{"artist":"Backstreet Boys","count":2,"stations":{"kol-hashfela":2},"title":"Show Me the Meaning of Being Lonely","prev":0},{"artist":"Teapacks","count":2,"stations":{"radio-tlv":1,"kol-hashfela":1},"title":"התחנה הישנה","prev":0},{"artist":"Sting","count":2,"stations":{"radio-darom":1,"kol-hashfela":1},"title":"Shape Of My Heart","prev":0},{"artist":"Djo","count":2,"stations":{"radio-tlv":2},"title":"End of Beginning","prev":0},{"artist":"alt-J","count":2,"stations":{"galil":1,"radio-tlv":1},"title":"Breezeblocks","prev":0},{"artist":"Hapil Shebaheder","count":2,"stations":{"galgalatz":2},"title":"גשם אחרון","prev":0},{"artist":"Michael Jackson","count":2,"stations":{"radio-darom":1,"kol-hashfela":1},"title":"Don't Stop 'Til You Get Enough","prev":0},{"artist":"Omer Adam","count":2,"stations":{"radio-darom":2},"title":"חי (שיר הנושא מתוך לשחרר את שולי סאן)","prev":0},{"artist":"Lana Del Rey","count":2,"stations":{"radio-tlv":1,"galgalatz":1},"title":"Summertime Sadness","prev":0},{"artist":"Noam Bettan & כאן - תאגיד השידור הישראלי","count":2,"stations":{"radio-tlv":2},"title":"Michelle","prev":0},{"artist":"George Michael","count":2,"stations":{"kol-hashfela":2},"title":"Father Figure","prev":0},{"artist":"Odeya","count":2,"stations":{"radio-darom":2},"title":"עשר רמות מעליו","prev":0},{"artist":"Stamatis Spanoudakis","count":2,"stations":{"kan-bet":2},"title":"Zi Ke Vasilevi","prev":0},{"artist":"Dire Straits","count":2,"stations":{"radio-tlv":1,"99fm":1},"title":"Sultans Of Swing","prev":0},{"artist":"Bonnie Tyler","count":2,"stations":{"kol-hashfela":2},"title":"Total Eclipse of the Heart","prev":0},{"artist":"INXS","count":2,"stations":{"kol-hashfela":1,"99fm":1},"title":"Never Tear Us Apart","prev":0},{"artist":"Tohar Kadosh","count":2,"stations":{"galgalatz":2},"title":"שמש","prev":0},{"artist":"Yehudit Ravitz & Ahuva Ozeri","count":2,"stations":{"radio-darom":2},"title":"האיש ההוא","prev":0},{"artist":"Tears for Fears","count":2,"stations":{"galgalatz":1,"galil":1},"title":"Sowing The Seeds Of Love","prev":0},{"artist":"Elai Botner and Yaldei Hachutz","count":2,"stations":{"radio-tlv":1,"galgalatz":1},"title":"תתן לי יד","prev":0},{"artist":"The Weeknd","count":2,"stations":{"galgalatz":1,"radio-tlv":1},"title":"Blinding Lights","prev":0},{"artist":"TLC","count":2,"stations":{"radio-tlv":1,"kol-hashfela":1},"title":"No Scrubs","prev":0},{"artist":"Eden Hason, Ofek Adanek & Agam Buhbut","count":2,"stations":{"radio-darom":1,"galgalatz":1},"title":"איך שהיא רוקדת","prev":0},{"artist":"Balkan Beat Box","count":2,"stations":{"galil":2},"title":"Habibi Min Zaman","prev":0},{"artist":"Hadag Nahash","count":2,"stations":{"radio-darom":1,"radio-tlv":1},"title":"לזוז (feat. MC שירי)","prev":0},{"artist":"Ishay Levi","count":2,"stations":{"radio-darom":1,"radio-tlv":1},"title":"Isha Neemana","prev":0},{"artist":"Reamonn","count":2,"stations":{"radio-tlv":1,"kol-hashfela":1},"title":"Supergirl","prev":0},{"artist":"Temper City","count":2,"stations":{"radio-tlv":2},"title":"Self Aware","prev":0},{"artist":"ABBA","count":2,"stations":{"radio-tlv":1,"kol-hashfela":1},"title":"Gimme! Gimme! Gimme! (A Man After Midnight)","prev":0}],"total_plays":1045},"30d":{"artists":[{"artist":"Faith No More","count":15,"stations":{"galgalatz":1,"99fm":1,"kan-88":13},"prev":0},{"artist":"Eyal Golan","count":10,"stations":{"radio-darom":10},"prev":0},{"artist":"Sting","count":8,"stations":{"galil":3,"kol-hashfela":3,"radio-darom":1,"99fm":1},"prev":0},{"artist":"Mark Lanegan","count":8,"stations":{"kan-88":8},"prev":0},{"artist":"Omer Adam","count":7,"stations":{"radio-darom":4,"galgalatz":1,"kan-bet":1,"radio-tlv":1},"prev":0},{"artist":"Teapacks","count":7,"stations":{"radio-tlv":1,"radio-darom":1,"kol-hashfela":3,"99fm":1,"galgalatz":1},"prev":0},{"artist":"David Bowie","count":7,"stations":{"radio-tlv":2,"99fm":2,"kol-hashfela":2,"kan-88":1},"prev":0},{"artist":"Dudu Tassa","count":6,"stations":{"99fm":1,"radio-tlv":3,"radio-darom":1,"galil":1},"prev":0},{"artist":"Madonna","count":6,"stations":{"kol-hashfela":3,"radio-tlv":1,"galgalatz":2},"prev":0},{"artist":"Tame Impala","count":6,"stations":{"radio-tlv":3,"galgalatz":1,"radio-darom":1,"kol-hashfela":1},"prev":0},{"artist":"Stevie Wonder","count":6,"stations":{"galil":1,"radio-tlv":1,"galgalatz":1,"kol-hashfela":2,"99fm":1},"prev":0},{"artist":"Peer Tasi","count":6,"stations":{"radio-darom":4,"kan-bet":1,"radio-tlv":1},"prev":0},{"artist":"Ehud Banai","count":6,"stations":{"kol-hashfela":1,"radio-darom":1,"99fm":2,"kan-88":1,"galil":1},"prev":0},{"artist":"Arik Einstein","count":5,"stations":{"radio-darom":1,"kan-88":4},"prev":0},{"artist":"Beyoncé","count":5,"stations":{"galil":2,"radio-darom":1,"galgalatz":1,"radio-tlv":1},"prev":0},{"artist":"Shlomo Artzi","count":5,"stations":{"kan-88":1,"galgalatz":1,"radio-darom":2,"kol-hashfela":1},"prev":0},{"artist":"ABBA","count":5,"stations":{"radio-tlv":3,"99fm":1,"kol-hashfela":1},"prev":0},{"artist":"Tuna","count":5,"stations":{"99fm":2,"kan-bet":1,"galgalatz":1,"radio-darom":1},"prev":0},{"artist":"Michael Jackson","count":5,"stations":{"radio-darom":1,"kol-hashfela":3,"radio-tlv":1},"prev":0},{"artist":"Renaissance","count":5,"stations":{"kan-88":5},"prev":0},{"artist":"Eden Ben Zaken","count":5,"stations":{"radio-tlv":2,"galgalatz":2,"radio-darom":1},"prev":0},{"artist":"Robert Wyatt","count":5,"stations":{"kan-88":5},"prev":0},{"artist":"Jasmin Moallem","count":5,"stations":{"kan-bet":1,"radio-tlv":1,"galil":1,"99fm":1,"galgalatz":1},"prev":0},{"artist":"The Beatles","count":4,"stations":{"radio-tlv":1,"99fm":2,"kan-bet":1},"prev":0},{"artist":"Corinne Allal","count":4,"stations":{"kol-hashfela":1,"radio-darom":1,"99fm":2},"prev":0},{"artist":"Eviatar Banai","count":4,"stations":{"kol-hashfela":2,"99fm":1,"radio-tlv":1},"prev":0},{"artist":"Nathan Goshen","count":4,"stations":{"kol-hashfela":2,"99fm":2},"prev":0},{"artist":"Pretenders","count":4,"stations":{"99fm":1,"kol-hashfela":1,"galil":2},"prev":0},{"artist":"Shuli Rand","count":4,"stations":{"radio-tlv":3,"kan-bet":1},"prev":0},{"artist":"Coldplay","count":4,"stations":{"kol-hashfela":1,"radio-darom":1,"radio-tlv":1,"99fm":1},"prev":0},{"artist":"Phil Collins","count":4,"stations":{"kol-hashfela":1,"radio-tlv":1,"99fm":1,"galil":1},"prev":0},{"artist":"Tears for Fears","count":4,"stations":{"galgalatz":1,"99fm":2,"galil":1},"prev":0},{"artist":"The Weeknd","count":4,"stations":{"99fm":1,"galgalatz":1,"radio-tlv":2},"prev":0},{"artist":"The Rolling Stones","count":4,"stations":{"galgalatz":1,"kan-88":1,"radio-tlv":1,"99fm":1},"prev":0},{"artist":"Loose Joints","count":4,"stations":{"kan-88":4},"prev":0},{"artist":"Ethnix","count":4,"stations":{"99fm":1,"kol-hashfela":2,"galgalatz":1},"prev":0},{"artist":"Yehudit Ravitz","count":3,"stations":{"99fm":3},"prev":0},{"artist":"Scorpions","count":3,"stations":{"kol-hashfela":1,"99fm":1,"radio-tlv":1},"prev":0},{"artist":"יובל מזרחי","count":3,"stations":{"radio-darom":3},"prev":0},{"artist":"Idan Raichel","count":3,"stations":{"radio-darom":2,"kol-hashfela":1},"prev":0},{"artist":"Bon Iver","count":3,"stations":{"99fm":2,"galil":1},"prev":0},{"artist":"Backstreet Boys","count":3,"stations":{"kol-hashfela":2,"radio-tlv":1},"prev":0},{"artist":"Izhar Ashdot","count":3,"stations":{"kol-hashfela":1,"galgalatz":1,"radio-tlv":1},"prev":0},{"artist":"Labrinth","count":3,"stations":{"galgalatz":3},"prev":0},{"artist":"Amir Dadon","count":3,"stations":{"radio-tlv":2,"99fm":1},"prev":0},{"artist":"Kings of Leon","count":3,"stations":{"radio-tlv":1,"99fm":1,"galil":1},"prev":0},{"artist":"Bee Gees","count":3,"stations":{"99fm":2,"radio-tlv":1},"prev":0},{"artist":"Lana Del Rey","count":3,"stations":{"radio-tlv":1,"galgalatz":1,"99fm":1},"prev":0},{"artist":"Radiohead","count":3,"stations":{"radio-tlv":1,"99fm":2},"prev":0},{"artist":"Odeya","count":3,"stations":{"radio-darom":3},"prev":0}],"songs":[{"artist":"Eyal Golan","count":7,"stations":{"radio-darom":7},"title":"מדע בדיוני","prev":0},{"artist":"Tame Impala","count":5,"stations":{"radio-tlv":3,"radio-darom":1,"kol-hashfela":1},"title":"Dracula","prev":0},{"artist":"Shuli Rand","count":4,"stations":{"radio-tlv":3,"kan-bet":1},"title":"לב לבן","prev":0},{"artist":"יובל מזרחי","count":3,"stations":{"radio-darom":3},"title":"דואט","prev":0},{"artist":"Labrinth","count":3,"stations":{"galgalatz":3},"title":"THE LIVING","prev":0},{"artist":"Dudu Tassa","count":3,"stations":{"radio-tlv":3},"title":"בית ביפו","prev":0},{"artist":"Mooki","count":3,"stations":{"radio-darom":1,"kan-88":1,"kol-hashfela":1},"title":"ילדה סוכר","prev":0},{"artist":"Jasmin Moallem","count":3,"stations":{"kan-bet":1,"radio-tlv":1,"galil":1},"title":"יהיה טוב","prev":0},{"artist":"Brill & Alona Haber","count":3,"stations":{"galgalatz":3},"title":"פרפר לבן","prev":0},{"artist":"The Doors","count":3,"stations":{"kan-88":3},"title":"Riders On The Storm","prev":0},{"artist":"Up, Bustle & Out","count":3,"stations":{"galil":3},"title":"Emerald Alley (Indian Morning Theme)","prev":0},{"artist":"Amy Winehouse","count":2,"stations":{"galgalatz":1,"99fm":1},"title":"You Know I'm No Good","prev":0},{"artist":"Eviatar Banai","count":2,"stations":{"kol-hashfela":2},"title":"יפה כלבנה","prev":0},{"artist":"Ran Danker","count":2,"stations":{"radio-tlv":1,"kol-hashfela":1},"title":"בית משוגעים","prev":0},{"artist":"Shlomo Artzi","count":2,"stations":{"kan-88":1,"radio-darom":1},"title":"תגידי","prev":0},{"artist":"Roie Shpigler & Ziv Moran","count":2,"stations":{"kan-bet":2},"title":"Northland","prev":0},{"artist":"ABBA","count":2,"stations":{"radio-tlv":2},"title":"Dancing Queen","prev":0},{"artist":"Ravid Plotnik","count":2,"stations":{"kol-hashfela":1,"99fm":1},"title":"‏שלווה בארמונותייך","prev":0},{"artist":"Scorpions","count":2,"stations":{"kol-hashfela":1,"radio-tlv":1},"title":"Still Loving You (Live)","prev":0},{"artist":"Prince","count":2,"stations":{"kol-hashfela":1,"galgalatz":1},"title":"Nothing Compares 2 U","prev":0},{"artist":"Idan Raichel","count":2,"stations":{"radio-darom":1,"kol-hashfela":1},"title":"Ahava Ka'zo (A Love Like This) [feat. זהבה בן]","prev":0},{"artist":"Backstreet Boys","count":2,"stations":{"kol-hashfela":2},"title":"Show Me the Meaning of Being Lonely","prev":0},{"artist":"Teapacks","count":2,"stations":{"radio-tlv":1,"kol-hashfela":1},"title":"התחנה הישנה","prev":0},{"artist":"Sting","count":2,"stations":{"radio-darom":1,"kol-hashfela":1},"title":"Shape Of My Heart","prev":0},{"artist":"Djo","count":2,"stations":{"radio-tlv":2},"title":"End of Beginning","prev":0},{"artist":"alt-J","count":2,"stations":{"galil":1,"radio-tlv":1},"title":"Breezeblocks","prev":0},{"artist":"Hapil Shebaheder","count":2,"stations":{"galgalatz":2},"title":"גשם אחרון","prev":0},{"artist":"Michael Jackson","count":2,"stations":{"radio-darom":1,"kol-hashfela":1},"title":"Don't Stop 'Til You Get Enough","prev":0},{"artist":"Omer Adam","count":2,"stations":{"radio-darom":2},"title":"חי (שיר הנושא מתוך לשחרר את שולי סאן)","prev":0},{"artist":"Lana Del Rey","count":2,"stations":{"radio-tlv":1,"galgalatz":1},"title":"Summertime Sadness","prev":0},{"artist":"Noam Bettan & כאן - תאגיד השידור הישראלי","count":2,"stations":{"radio-tlv":2},"title":"Michelle","prev":0},{"artist":"George Michael","count":2,"stations":{"kol-hashfela":2},"title":"Father Figure","prev":0},{"artist":"Odeya","count":2,"stations":{"radio-darom":2},"title":"עשר רמות מעליו","prev":0},{"artist":"Stamatis Spanoudakis","count":2,"stations":{"kan-bet":2},"title":"Zi Ke Vasilevi","prev":0},{"artist":"Dire Straits","count":2,"stations":{"radio-tlv":1,"99fm":1},"title":"Sultans Of Swing","prev":0},{"artist":"Bonnie Tyler","count":2,"stations":{"kol-hashfela":2},"title":"Total Eclipse of the Heart","prev":0},{"artist":"INXS","count":2,"stations":{"kol-hashfela":1,"99fm":1},"title":"Never Tear Us Apart","prev":0},{"artist":"Tohar Kadosh","count":2,"stations":{"galgalatz":2},"title":"שמש","prev":0},{"artist":"Yehudit Ravitz & Ahuva Ozeri","count":2,"stations":{"radio-darom":2},"title":"האיש ההוא","prev":0},{"artist":"Tears for Fears","count":2,"stations":{"galgalatz":1,"galil":1},"title":"Sowing The Seeds Of Love","prev":0},{"artist":"Elai Botner and Yaldei Hachutz","count":2,"stations":{"radio-tlv":1,"galgalatz":1},"title":"תתן לי יד","prev":0},{"artist":"The Weeknd","count":2,"stations":{"galgalatz":1,"radio-tlv":1},"title":"Blinding Lights","prev":0},{"artist":"TLC","count":2,"stations":{"radio-tlv":1,"kol-hashfela":1},"title":"No Scrubs","prev":0},{"artist":"Eden Hason, Ofek Adanek & Agam Buhbut","count":2,"stations":{"radio-darom":1,"galgalatz":1},"title":"איך שהיא רוקדת","prev":0},{"artist":"Balkan Beat Box","count":2,"stations":{"galil":2},"title":"Habibi Min Zaman","prev":0},{"artist":"Hadag Nahash","count":2,"stations":{"radio-darom":1,"radio-tlv":1},"title":"לזוז (feat. MC שירי)","prev":0},{"artist":"Ishay Levi","count":2,"stations":{"radio-darom":1,"radio-tlv":1},"title":"Isha Neemana","prev":0},{"artist":"Reamonn","count":2,"stations":{"radio-tlv":1,"kol-hashfela":1},"title":"Supergirl","prev":0},{"artist":"Temper City","count":2,"stations":{"radio-tlv":2},"title":"Self Aware","prev":0},{"artist":"ABBA","count":2,"stations":{"radio-tlv":1,"kol-hashfela":1},"title":"Gimme! Gimme! Gimme! (A Man After Midnight)","prev":0}],"total_plays":1045},"all":{"artists":[{"artist":"Faith No More","count":15,"stations":{"galgalatz":1,"99fm":1,"kan-88":13},"prev":0},{"artist":"Eyal Golan","count":10,"stations":{"radio-darom":10},"prev":0},{"artist":"Sting","count":8,"stations":{"galil":3,"kol-hashfela":3,"radio-darom":1,"99fm":1},"prev":0},{"artist":"Mark Lanegan","count":8,"stations":{"kan-88":8},"prev":0},{"artist":"Omer Adam","count":7,"stations":{"radio-darom":4,"galgalatz":1,"kan-bet":1,"radio-tlv":1},"prev":0},{"artist":"Teapacks","count":7,"stations":{"radio-tlv":1,"radio-darom":1,"kol-hashfela":3,"99fm":1,"galgalatz":1},"prev":0},{"artist":"David Bowie","count":7,"stations":{"radio-tlv":2,"99fm":2,"kol-hashfela":2,"kan-88":1},"prev":0},{"artist":"Dudu Tassa","count":6,"stations":{"99fm":1,"radio-tlv":3,"radio-darom":1,"galil":1},"prev":0},{"artist":"Madonna","count":6,"stations":{"kol-hashfela":3,"radio-tlv":1,"galgalatz":2},"prev":0},{"artist":"Tame Impala","count":6,"stations":{"radio-tlv":3,"galgalatz":1,"radio-darom":1,"kol-hashfela":1},"prev":0},{"artist":"Stevie Wonder","count":6,"stations":{"galil":1,"radio-tlv":1,"galgalatz":1,"kol-hashfela":2,"99fm":1},"prev":0},{"artist":"Peer Tasi","count":6,"stations":{"radio-darom":4,"kan-bet":1,"radio-tlv":1},"prev":0},{"artist":"Ehud Banai","count":6,"stations":{"kol-hashfela":1,"radio-darom":1,"99fm":2,"kan-88":1,"galil":1},"prev":0},{"artist":"Arik Einstein","count":5,"stations":{"radio-darom":1,"kan-88":4},"prev":0},{"artist":"Beyoncé","count":5,"stations":{"galil":2,"radio-darom":1,"galgalatz":1,"radio-tlv":1},"prev":0},{"artist":"Shlomo Artzi","count":5,"stations":{"kan-88":1,"galgalatz":1,"radio-darom":2,"kol-hashfela":1},"prev":0},{"artist":"ABBA","count":5,"stations":{"radio-tlv":3,"99fm":1,"kol-hashfela":1},"prev":0},{"artist":"Tuna","count":5,"stations":{"99fm":2,"kan-bet":1,"galgalatz":1,"radio-darom":1},"prev":0},{"artist":"Michael Jackson","count":5,"stations":{"radio-darom":1,"kol-hashfela":3,"radio-tlv":1},"prev":0},{"artist":"Renaissance","count":5,"stations":{"kan-88":5},"prev":0},{"artist":"Eden Ben Zaken","count":5,"stations":{"radio-tlv":2,"galgalatz":2,"radio-darom":1},"prev":0},{"artist":"Robert Wyatt","count":5,"stations":{"kan-88":5},"prev":0},{"artist":"Jasmin Moallem","count":5,"stations":{"kan-bet":1,"radio-tlv":1,"galil":1,"99fm":1,"galgalatz":1},"prev":0},{"artist":"The Beatles","count":4,"stations":{"radio-tlv":1,"99fm":2,"kan-bet":1},"prev":0},{"artist":"Corinne Allal","count":4,"stations":{"kol-hashfela":1,"radio-darom":1,"99fm":2},"prev":0},{"artist":"Eviatar Banai","count":4,"stations":{"kol-hashfela":2,"99fm":1,"radio-tlv":1},"prev":0},{"artist":"Nathan Goshen","count":4,"stations":{"kol-hashfela":2,"99fm":2},"prev":0},{"artist":"Pretenders","count":4,"stations":{"99fm":1,"kol-hashfela":1,"galil":2},"prev":0},{"artist":"Shuli Rand","count":4,"stations":{"radio-tlv":3,"kan-bet":1},"prev":0},{"artist":"Coldplay","count":4,"stations":{"kol-hashfela":1,"radio-darom":1,"radio-tlv":1,"99fm":1},"prev":0},{"artist":"Phil Collins","count":4,"stations":{"kol-hashfela":1,"radio-tlv":1,"99fm":1,"galil":1},"prev":0},{"artist":"Tears for Fears","count":4,"stations":{"galgalatz":1,"99fm":2,"galil":1},"prev":0},{"artist":"The Weeknd","count":4,"stations":{"99fm":1,"galgalatz":1,"radio-tlv":2},"prev":0},{"artist":"The Rolling Stones","count":4,"stations":{"galgalatz":1,"kan-88":1,"radio-tlv":1,"99fm":1},"prev":0},{"artist":"Loose Joints","count":4,"stations":{"kan-88":4},"prev":0},{"artist":"Ethnix","count":4,"stations":{"99fm":1,"kol-hashfela":2,"galgalatz":1},"prev":0},{"artist":"Yehudit Ravitz","count":3,"stations":{"99fm":3},"prev":0},{"artist":"Scorpions","count":3,"stations":{"kol-hashfela":1,"99fm":1,"radio-tlv":1},"prev":0},{"artist":"יובל מזרחי","count":3,"stations":{"radio-darom":3},"prev":0},{"artist":"Idan Raichel","count":3,"stations":{"radio-darom":2,"kol-hashfela":1},"prev":0},{"artist":"Bon Iver","count":3,"stations":{"99fm":2,"galil":1},"prev":0},{"artist":"Backstreet Boys","count":3,"stations":{"kol-hashfela":2,"radio-tlv":1},"prev":0},{"artist":"Izhar Ashdot","count":3,"stations":{"kol-hashfela":1,"galgalatz":1,"radio-tlv":1},"prev":0},{"artist":"Labrinth","count":3,"stations":{"galgalatz":3},"prev":0},{"artist":"Amir Dadon","count":3,"stations":{"radio-tlv":2,"99fm":1},"prev":0},{"artist":"Kings of Leon","count":3,"stations":{"radio-tlv":1,"99fm":1,"galil":1},"prev":0},{"artist":"Bee Gees","count":3,"stations":{"99fm":2,"radio-tlv":1},"prev":0},{"artist":"Lana Del Rey","count":3,"stations":{"radio-tlv":1,"galgalatz":1,"99fm":1},"prev":0},{"artist":"Radiohead","count":3,"stations":{"radio-tlv":1,"99fm":2},"prev":0},{"artist":"Odeya","count":3,"stations":{"radio-darom":3},"prev":0}],"songs":[{"artist":"Eyal Golan","count":7,"stations":{"radio-darom":7},"title":"מדע בדיוני","prev":0},{"artist":"Tame Impala","count":5,"stations":{"radio-tlv":3,"radio-darom":1,"kol-hashfela":1},"title":"Dracula","prev":0},{"artist":"Shuli Rand","count":4,"stations":{"radio-tlv":3,"kan-bet":1},"title":"לב לבן","prev":0},{"artist":"יובל מזרחי","count":3,"stations":{"radio-darom":3},"title":"דואט","prev":0},{"artist":"Labrinth","count":3,"stations":{"galgalatz":3},"title":"THE LIVING","prev":0},{"artist":"Dudu Tassa","count":3,"stations":{"radio-tlv":3},"title":"בית ביפו","prev":0},{"artist":"Mooki","count":3,"stations":{"radio-darom":1,"kan-88":1,"kol-hashfela":1},"title":"ילדה סוכר","prev":0},{"artist":"Jasmin Moallem","count":3,"stations":{"kan-bet":1,"radio-tlv":1,"galil":1},"title":"יהיה טוב","prev":0},{"artist":"Brill & Alona Haber","count":3,"stations":{"galgalatz":3},"title":"פרפר לבן","prev":0},{"artist":"The Doors","count":3,"stations":{"kan-88":3},"title":"Riders On The Storm","prev":0},{"artist":"Up, Bustle & Out","count":3,"stations":{"galil":3},"title":"Emerald Alley (Indian Morning Theme)","prev":0},{"artist":"Amy Winehouse","count":2,"stations":{"galgalatz":1,"99fm":1},"title":"You Know I'm No Good","prev":0},{"artist":"Eviatar Banai","count":2,"stations":{"kol-hashfela":2},"title":"יפה כלבנה","prev":0},{"artist":"Ran Danker","count":2,"stations":{"radio-tlv":1,"kol-hashfela":1},"title":"בית משוגעים","prev":0},{"artist":"Shlomo Artzi","count":2,"stations":{"kan-88":1,"radio-darom":1},"title":"תגידי","prev":0},{"artist":"Roie Shpigler & Ziv Moran","count":2,"stations":{"kan-bet":2},"title":"Northland","prev":0},{"artist":"ABBA","count":2,"stations":{"radio-tlv":2},"title":"Dancing Queen","prev":0},{"artist":"Ravid Plotnik","count":2,"stations":{"kol-hashfela":1,"99fm":1},"title":"‏שלווה בארמונותייך","prev":0},{"artist":"Scorpions","count":2,"stations":{"kol-hashfela":1,"radio-tlv":1},"title":"Still Loving You (Live)","prev":0},{"artist":"Prince","count":2,"stations":{"kol-hashfela":1,"galgalatz":1},"title":"Nothing Compares 2 U","prev":0},{"artist":"Idan Raichel","count":2,"stations":{"radio-darom":1,"kol-hashfela":1},"title":"Ahava Ka'zo (A Love Like This) [feat. זהבה בן]","prev":0},{"artist":"Backstreet Boys","count":2,"stations":{"kol-hashfela":2},"title":"Show Me the Meaning of Being Lonely","prev":0},{"artist":"Teapacks","count":2,"stations":{"radio-tlv":1,"kol-hashfela":1},"title":"התחנה הישנה","prev":0},{"artist":"Sting","count":2,"stations":{"radio-darom":1,"kol-hashfela":1},"title":"Shape Of My Heart","prev":0},{"artist":"Djo","count":2,"stations":{"radio-tlv":2},"title":"End of Beginning","prev":0},{"artist":"alt-J","count":2,"stations":{"galil":1,"radio-tlv":1},"title":"Breezeblocks","prev":0},{"artist":"Hapil Shebaheder","count":2,"stations":{"galgalatz":2},"title":"גשם אחרון","prev":0},{"artist":"Michael Jackson","count":2,"stations":{"radio-darom":1,"kol-hashfela":1},"title":"Don't Stop 'Til You Get Enough","prev":0},{"artist":"Omer Adam","count":2,"stations":{"radio-darom":2},"title":"חי (שיר הנושא מתוך לשחרר את שולי סאן)","prev":0},{"artist":"Lana Del Rey","count":2,"stations":{"radio-tlv":1,"galgalatz":1},"title":"Summertime Sadness","prev":0},{"artist":"Noam Bettan & כאן - תאגיד השידור הישראלי","count":2,"stations":{"radio-tlv":2},"title":"Michelle","prev":0},{"artist":"George Michael","count":2,"stations":{"kol-hashfela":2},"title":"Father Figure","prev":0},{"artist":"Odeya","count":2,"stations":{"radio-darom":2},"title":"עשר רמות מעליו","prev":0},{"artist":"Stamatis Spanoudakis","count":2,"stations":{"kan-bet":2},"title":"Zi Ke Vasilevi","prev":0},{"artist":"Dire Straits","count":2,"stations":{"radio-tlv":1,"99fm":1},"title":"Sultans Of Swing","prev":0},{"artist":"Bonnie Tyler","count":2,"stations":{"kol-hashfela":2},"title":"Total Eclipse of the Heart","prev":0},{"artist":"INXS","count":2,"stations":{"kol-hashfela":1,"99fm":1},"title":"Never Tear Us Apart","prev":0},{"artist":"Tohar Kadosh","count":2,"stations":{"galgalatz":2},"title":"שמש","prev":0},{"artist":"Yehudit Ravitz & Ahuva Ozeri","count":2,"stations":{"radio-darom":2},"title":"האיש ההוא","prev":0},{"artist":"Tears for Fears","count":2,"stations":{"galgalatz":1,"galil":1},"title":"Sowing The Seeds Of Love","prev":0},{"artist":"Elai Botner and Yaldei Hachutz","count":2,"stations":{"radio-tlv":1,"galgalatz":1},"title":"תתן לי יד","prev":0},{"artist":"The Weeknd","count":2,"stations":{"galgalatz":1,"radio-tlv":1},"title":"Blinding Lights","prev":0},{"artist":"TLC","count":2,"stations":{"radio-tlv":1,"kol-hashfela":1},"title":"No Scrubs","prev":0},{"artist":"Eden Hason, Ofek Adanek & Agam Buhbut","count":2,"stations":{"radio-darom":1,"galgalatz":1},"title":"איך שהיא רוקדת","prev":0},{"artist":"Balkan Beat Box","count":2,"stations":{"galil":2},"title":"Habibi Min Zaman","prev":0},{"artist":"Hadag Nahash","count":2,"stations":{"radio-darom":1,"radio-tlv":1},"title":"לזוז (feat. MC שירי)","prev":0},{"artist":"Ishay Levi","count":2,"stations":{"radio-darom":1,"radio-tlv":1},"title":"Isha Neemana","prev":0},{"artist":"Reamonn","count":2,"stations":{"radio-tlv":1,"kol-hashfela":1},"title":"Supergirl","prev":0},{"artist":"Temper City","count":2,"stations":{"radio-tlv":2},"title":"Self Aware","prev":0},{"artist":"ABBA","count":2,"stations":{"radio-tlv":1,"kol-hashfela":1},"title":"Gimme! Gimme! Gimme! (A Man After Midnight)","prev":0}],"total_plays":1045}}}
